mozi_ai_sdk/__init__.py
mozi_ai_sdk/base_env.py
mozi_ai_sdk/bt_test/__init__.py
mozi_ai_sdk/bt_test/error.log
mozi_ai_sdk/bt_test/main_versus.py
mozi_ai_sdk/bt_test/readme
mozi_ai_sdk/bt_test/env/__init__.py
mozi_ai_sdk/bt_test/env/env.py
mozi_ai_sdk/bt_test/env/etc.py
mozi_ai_sdk/bt_test/scen_file/__init__.py
mozi_ai_sdk/bt_test/scen_file/hxfb-multitask.xml
mozi_ai_sdk/bt_test/scen_file/海峡风暴-资格选拔赛-蓝方任务随机方案-给周国进测试.scen
mozi_ai_sdk/bt_test/utils/__init__.py
mozi_ai_sdk/bt_test/utils/bt_agent_antiship.py
mozi_ai_sdk/bt_test/utils/leaf_nodes_eg.py
mozi_ai_sdk/btmodel/__init__.py
mozi_ai_sdk/btmodel/bt/__init__.py
mozi_ai_sdk/btmodel/bt/arlib.py
mozi_ai_sdk/btmodel/bt/basic.py
mozi_ai_sdk/btmodel/bt/bt_nodes.py
mozi_ai_sdk/btmodel/bt/detail.py
mozi_ai_sdk/btmodel/bt/utils.py
mozi_ai_sdk/dppo/__init__.py
mozi_ai_sdk/dppo/main_versus.py
mozi_ai_sdk/dppo/readme
mozi_ai_sdk/dppo/train_ppo.py
mozi_ai_sdk/dppo/train_ray.py
mozi_ai_sdk/dppo/agents/__init__.py
mozi_ai_sdk/dppo/agents/ppo_agent.py
mozi_ai_sdk/dppo/agents/ppo_policies.py
mozi_ai_sdk/dppo/agents/replay_memory.py
mozi_ai_sdk/dppo/agents/utils_tf.py
mozi_ai_sdk/dppo/bin/__init__.py
mozi_ai_sdk/dppo/bin/checkpoints/__init__.py
mozi_ai_sdk/dppo/bin/checkpoints/checkpoint-5000
mozi_ai_sdk/dppo/bin/tfevents_ppo/__init__.py
mozi_ai_sdk/dppo/envs/__init__.py
mozi_ai_sdk/dppo/envs/env.py
mozi_ai_sdk/dppo/envs/env_remote.py
mozi_ai_sdk/dppo/envs/etc.py
mozi_ai_sdk/dppo/envs/observations.py
mozi_ai_sdk/dppo/envs/tasks.py
mozi_ai_sdk/dppo/envs/utils.py
mozi_ai_sdk/dppo/envs/spaces/__init__.py
mozi_ai_sdk/dppo/envs/spaces/mask_discrete.py
mozi_ai_sdk/dppo/envs/spaces/pysc2_raw.py
mozi_ai_sdk/dppo/utils/__init__.py
mozi_ai_sdk/dppo/utils/ray_test.py
mozi_ai_sdk/dppo/utils/utils.py
mozi_ai_sdk/heli_anti_sub/__init__.py
mozi_ai_sdk/heli_anti_sub/man_versus.py
mozi_ai_sdk/heli_anti_sub/readme
mozi_ai_sdk/heli_anti_sub/env/__init__.py
mozi_ai_sdk/heli_anti_sub/env/env.py
mozi_ai_sdk/heli_anti_sub/env/etc.py
mozi_ai-0.1.1.4.dist-info/LICENSE
mozi_ai-0.1.1.4.dist-info/METADATA
mozi_ai-0.1.1.4.dist-info/WHEEL
mozi_ai-0.1.1.4.dist-info/top_level.txt
mozi_ai-0.1.1.4.dist-info/RECORD
